celadon/__about__.py
celadon/__init__.py
celadon/application.py
celadon/enums.py
celadon/frames.py
celadon/palette.py
celadon/py.typed
celadon/state_machine.py
celadon/style_map.py
celadon/widgets/__init__.py
celadon/widgets/button.py
celadon/widgets/checkbox.py
celadon/widgets/container.py
celadon/widgets/dialogue.py
celadon/widgets/dropdown.py
celadon/widgets/field.py
celadon/widgets/link.py
celadon/widgets/progress.py
celadon/widgets/slider.py
celadon/widgets/text.py
celadon/widgets/widget.py
tests/__init__.py
tests/test_state_machine.py
tests/test_widget.py
sh40_celadon-0.10.0.dist-info/METADATA
sh40_celadon-0.10.0.dist-info/WHEEL
sh40_celadon-0.10.0.dist-info/licenses/LICENSE.txt
sh40_celadon-0.10.0.dist-info/RECORD
