Metadata-Version: 2.4
Name: sh40-celadon
Version: 0.10.0
Summary: A modern TUI library taking the right lessons from the web.
Project-URL: Documentation, https://github.com/shade40/celadon#readme
Project-URL: Issues, https://github.com/shade40/celadon/issues
Project-URL: Source, https://github.com/shade40/celadon
Author-email: bczsalba <bczsalba@gmail.com>
License-Expression: MIT
License-File: LICENSE.txt
Classifier: Development Status :: 4 - Beta
Classifier: Environment :: Console
Classifier: Intended Audience :: Developers
Classifier: License :: OSI Approved :: MIT License
Classifier: Operating System :: MacOS
Classifier: Operating System :: POSIX :: Linux
Classifier: Programming Language :: Python
Classifier: Programming Language :: Python :: 3.8
Classifier: Programming Language :: Python :: 3.9
Classifier: Programming Language :: Python :: 3.10
Classifier: Programming Language :: Python :: 3.11
Classifier: Programming Language :: Python :: Implementation :: CPython
Classifier: Programming Language :: Python :: Implementation :: PyPy
Classifier: Topic :: Software Development :: Libraries
Classifier: Topic :: Terminals
Classifier: Topic :: Text Processing :: Markup
Classifier: Typing :: Typed
Requires-Python: >=3.8
Requires-Dist: pyyaml
Requires-Dist: sh40-slate
Requires-Dist: sh40-zenith
